keras_tuner/__init__.py
keras_tuner/applications/__init__.py
keras_tuner/engine/__init__.py
keras_tuner/engine/base_tuner/__init__.py
keras_tuner/engine/hypermodel/__init__.py
keras_tuner/engine/hyperparameters/__init__.py
keras_tuner/engine/metrics_tracking/__init__.py
keras_tuner/engine/oracle/__init__.py
keras_tuner/engine/trial/__init__.py
keras_tuner/engine/tuner/__init__.py
keras_tuner/errors/__init__.py
keras_tuner/oracles/__init__.py
keras_tuner/src/__init__.py
keras_tuner/src/api_export.py
keras_tuner/src/config.py
keras_tuner/src/errors.py
keras_tuner/src/utils.py
keras_tuner/src/version.py
keras_tuner/src/applications/__init__.py
keras_tuner/src/applications/augment.py
keras_tuner/src/applications/efficientnet.py
keras_tuner/src/applications/resnet.py
keras_tuner/src/applications/xception.py
keras_tuner/src/backend/__init__.py
keras_tuner/src/backend/config.py
keras_tuner/src/backend/io.py
keras_tuner/src/backend/keras.py
keras_tuner/src/backend/ops.py
keras_tuner/src/backend/random.py
keras_tuner/src/distribute/__init__.py
keras_tuner/src/distribute/oracle_chief.py
keras_tuner/src/distribute/oracle_client.py
keras_tuner/src/distribute/utils.py
keras_tuner/src/engine/__init__.py
keras_tuner/src/engine/base_tuner.py
keras_tuner/src/engine/conditions.py
keras_tuner/src/engine/hypermodel.py
keras_tuner/src/engine/metrics_tracking.py
keras_tuner/src/engine/objective.py
keras_tuner/src/engine/oracle.py
keras_tuner/src/engine/stateful.py
keras_tuner/src/engine/trial.py
keras_tuner/src/engine/tuner.py
keras_tuner/src/engine/tuner_utils.py
keras_tuner/src/engine/hyperparameters/__init__.py
keras_tuner/src/engine/hyperparameters/hp_utils.py
keras_tuner/src/engine/hyperparameters/hyperparameter.py
keras_tuner/src/engine/hyperparameters/hyperparameters.py
keras_tuner/src/engine/hyperparameters/hp_types/__init__.py
keras_tuner/src/engine/hyperparameters/hp_types/boolean_hp.py
keras_tuner/src/engine/hyperparameters/hp_types/choice_hp.py
keras_tuner-1.4.7.dist-info/METADATA
keras_tuner-1.4.7.dist-info/WHEEL
keras_tuner-1.4.7.dist-info/top_level.txt
keras_tuner-1.4.7.dist-info/RECORD
